donotation/__init__.py
donotation/py.typed
donotation-0.0.10.dist-info/METADATA
donotation-0.0.10.dist-info/WHEEL
donotation-0.0.10.dist-info/licenses/LICENCE
donotation-0.0.10.dist-info/RECORD
