Metadata-Version: 2.3
Name: donotation
Version: 0.0.10
Summary: A library that introduces the Haskell-like do notation using a Python decorator.
Project-URL: Homepage, https://github.com/MichaelSchneeberger/do-notation
Author-email: Michael Schneeberger <michael.schneeb@hotmail.com>
License-File: LICENCE
Requires-Python: >=3.12
